{
  "songId": "Polumnia Omnia.mp3",
  "notes": [
    {
      "time": 1523,
      "lane": "d"
    },
    {
      "time": 1579,
      "lane": "j"
    },
    {
      "time": 1701,
      "lane": "j"
    },
    {
      "time": 1834,
      "lane": "j"
    },
    {
      "time": 1968,
      "lane": "d"
    },
    {
      "time": 2065,
      "lane": "k"
    },
    {
      "time": 2213,
      "lane": "k"
    },
    {
      "time": 2495,
      "lane": "f"
    },
    {
      "time": 2679,
      "lane": "f"
    },
    {
      "time": 2992,
      "lane": "j"
    },
    {
      "time": 3517,
      "lane": "d"
    },
    {
      "time": 3852,
      "lane": "j"
    },
    {
      "time": 4107,
      "lane": "f"
    },
    {
      "time": 4143,
      "lane": "k"
    },
    {
      "time": 4280,
      "lane": "f"
    },
    {
      "time": 4295,
      "lane": "k"
    },
    {
      "time": 4450,
      "lane": "k"
    },
    {
      "time": 4476,
      "lane": "d"
    },
    {
      "time": 4968,
      "lane": "k"
    },
    {
      "time": 5058,
      "lane": "f"
    },
    {
      "time": 5350,
      "lane": "k"
    },
    {
      "time": 5498,
      "lane": "k"
    },
    {
      "time": 5576,
      "lane": "d",
      "type": "hold",
      "duration": 339
    },
    {
      "time": 5929,
      "lane": "j",
      "type": "hold",
      "duration": 358
    },
    {
      "time": 6422,
      "lane": "f"
    },
    {
      "time": 6533,
      "lane": "k"
    },
    {
      "time": 6644,
      "lane": "f"
    },
    {
      "time": 6862,
      "lane": "k"
    },
    {
      "time": 6988,
      "lane": "f"
    },
    {
      "time": 7011,
      "lane": "k"
    },
    {
      "time": 7392,
      "lane": "d",
      "type": "hold",
      "duration": 2670
    },
    {
      "time": 7415,
      "lane": "k",
      "type": "hold",
      "duration": 359
    },
    {
      "time": 8044,
      "lane": "j"
    },
    {
      "time": 8290,
      "lane": "k",
      "type": "hold",
      "duration": 1763
    },
    {
      "time": 10369,
      "lane": "f",
      "type": "hold",
      "duration": 2738
    },
    {
      "time": 10409,
      "lane": "k",
      "type": "hold",
      "duration": 355
    },
    {
      "time": 10972,
      "lane": "j"
    },
    {
      "time": 11109,
      "lane": "d",
      "type": "hold",
      "duration": 1997
    },
    {
      "time": 11207,
      "lane": "k",
      "type": "hold",
      "duration": 1884
    },
    {
      "time": 13421,
      "lane": "f",
      "type": "hold",
      "duration": 2352
    },
    {
      "time": 13448,
      "lane": "k",
      "type": "hold",
      "duration": 2296
    },
    {
      "time": 16054,
      "lane": "j"
    },
    {
      "time": 16144,
      "lane": "f"
    },
    {
      "time": 16302,
      "lane": "d",
      "type": "hold",
      "duration": 2728
    },
    {
      "time": 16460,
      "lane": "k",
      "type": "hold",
      "duration": 2570
    },
    {
      "time": 19437,
      "lane": "j"
    },
    {
      "time": 19452,
      "lane": "f"
    },
    {
      "time": 19603,
      "lane": "j"
    },
    {
      "time": 19784,
      "lane": "k"
    },
    {
      "time": 19869,
      "lane": "d"
    },
    {
      "time": 19956,
      "lane": "k"
    },
    {
      "time": 20105,
      "lane": "k"
    },
    {
      "time": 20305,
      "lane": "k"
    },
    {
      "time": 20509,
      "lane": "f",
      "type": "hold",
      "duration": 356
    },
    {
      "time": 20892,
      "lane": "j"
    },
    {
      "time": 21040,
      "lane": "j"
    },
    {
      "time": 21224,
      "lane": "d"
    },
    {
      "time": 21382,
      "lane": "k"
    },
    {
      "time": 21534,
      "lane": "d"
    },
    {
      "time": 21727,
      "lane": "k"
    },
    {
      "time": 21912,
      "lane": "k"
    },
    {
      "time": 22033,
      "lane": "f"
    },
    {
      "time": 22225,
      "lane": "j"
    },
    {
      "time": 22407,
      "lane": "f"
    },
    {
      "time": 22564,
      "lane": "k"
    },
    {
      "time": 22740,
      "lane": "k"
    },
    {
      "time": 22897,
      "lane": "k"
    },
    {
      "time": 23007,
      "lane": "d"
    },
    {
      "time": 23278,
      "lane": "d"
    },
    {
      "time": 23411,
      "lane": "j"
    },
    {
      "time": 23546,
      "lane": "j"
    },
    {
      "time": 23694,
      "lane": "j"
    },
    {
      "time": 23867,
      "lane": "f"
    },
    {
      "time": 24016,
      "lane": "k"
    },
    {
      "time": 24150,
      "lane": "k"
    },
    {
      "time": 24309,
      "lane": "f"
    },
    {
      "time": 24526,
      "lane": "j"
    },
    {
      "time": 24684,
      "lane": "f"
    },
    {
      "time": 24863,
      "lane": "k"
    },
    {
      "time": 25038,
      "lane": "d"
    },
    {
      "time": 25209,
      "lane": "j"
    },
    {
      "time": 25355,
      "lane": "d",
      "type": "hold",
      "duration": 2382
    },
    {
      "time": 25443,
      "lane": "k",
      "type": "hold",
      "duration": 2238
    },
    {
      "time": 26562,
      "lane": "f"
    },
    {
      "time": 26945,
      "lane": "j"
    },
    {
      "time": 27179,
      "lane": "j"
    },
    {
      "time": 27439,
      "lane": "j"
    },
    {
      "time": 27525,
      "lane": "f"
    },
    {
      "time": 27841,
      "lane": "j"
    },
    {
      "time": 28002,
      "lane": "f",
      "type": "hold",
      "duration": 461
    },
    {
      "time": 28409,
      "lane": "k",
      "type": "hold",
      "duration": 2228
    },
    {
      "time": 29491,
      "lane": "d"
    },
    {
      "time": 29852,
      "lane": "d"
    },
    {
      "time": 30168,
      "lane": "j"
    },
    {
      "time": 30256,
      "lane": "f"
    },
    {
      "time": 30661,
      "lane": "d"
    },
    {
      "time": 30856,
      "lane": "k"
    },
    {
      "time": 31006,
      "lane": "d",
      "type": "hold",
      "duration": 2466
    },
    {
      "time": 31403,
      "lane": "j",
      "type": "hold",
      "duration": 1877
    },
    {
      "time": 31990,
      "lane": "f"
    },
    {
      "time": 32345,
      "lane": "k"
    },
    {
      "time": 32530,
      "lane": "f"
    },
    {
      "time": 32840,
      "lane": "k"
    },
    {
      "time": 33182,
      "lane": "k"
    },
    {
      "time": 33429,
      "lane": "j"
    },
    {
      "time": 33473,
      "lane": "k"
    },
    {
      "time": 33725,
      "lane": "f"
    },
    {
      "time": 33878,
      "lane": "j"
    },
    {
      "time": 34007,
      "lane": "k",
      "type": "hold",
      "duration": 383
    },
    {
      "time": 34410,
      "lane": "f",
      "type": "hold",
      "duration": 2112
    },
    {
      "time": 34758,
      "lane": "j"
    },
    {
      "time": 34918,
      "lane": "k"
    },
    {
      "time": 35299,
      "lane": "k"
    },
    {
      "time": 35425,
      "lane": "k"
    },
    {
      "time": 35880,
      "lane": "j"
    },
    {
      "time": 35894,
      "lane": "d"
    },
    {
      "time": 36196,
      "lane": "k"
    },
    {
      "time": 36493,
      "lane": "j"
    },
    {
      "time": 36752,
      "lane": "f"
    },
    {
      "time": 36889,
      "lane": "k"
    },
    {
      "time": 37022,
      "lane": "f",
      "type": "hold",
      "duration": 409
    },
    {
      "time": 37416,
      "lane": "j"
    },
    {
      "time": 37567,
      "lane": "j"
    },
    {
      "time": 37774,
      "lane": "d"
    },
    {
      "time": 37801,
      "lane": "k"
    },
    {
      "time": 37957,
      "lane": "k"
    },
    {
      "time": 38156,
      "lane": "f"
    },
    {
      "time": 38465,
      "lane": "j"
    },
    {
      "time": 38584,
      "lane": "f"
    },
    {
      "time": 38599,
      "lane": "j"
    },
    {
      "time": 38744,
      "lane": "j"
    },
    {
      "time": 38886,
      "lane": "k"
    },
    {
      "time": 38983,
      "lane": "f"
    },
    {
      "time": 39078,
      "lane": "k"
    },
    {
      "time": 39215,
      "lane": "k"
    },
    {
      "time": 39347,
      "lane": "f"
    },
    {
      "time": 39497,
      "lane": "j"
    },
    {
      "time": 39631,
      "lane": "d",
      "type": "hold",
      "duration": 508
    },
    {
      "time": 39792,
      "lane": "k",
      "type": "hold",
      "duration": 318
    },
    {
      "time": 40380,
      "lane": "f",
      "type": "hold",
      "duration": 1924
    },
    {
      "time": 40416,
      "lane": "j",
      "type": "hold",
      "duration": 593
    },
    {
      "time": 40899,
      "lane": "k"
    },
    {
      "time": 41233,
      "lane": "k"
    },
    {
      "time": 41429,
      "lane": "k"
    },
    {
      "time": 41539,
      "lane": "k"
    },
    {
      "time": 41875,
      "lane": "j",
      "type": "hold",
      "duration": 395
    },
    {
      "time": 41878,
      "lane": "d",
      "type": "hold",
      "duration": 388
    },
    {
      "time": 42611,
      "lane": "f",
      "type": "hold",
      "duration": 443
    },
    {
      "time": 42644,
      "lane": "k",
      "type": "hold",
      "duration": 397
    },
    {
      "time": 43396,
      "lane": "k",
      "type": "hold",
      "duration": 1160
    },
    {
      "time": 43419,
      "lane": "j",
      "type": "hold",
      "duration": 1161
    },
    {
      "time": 43444,
      "lane": "d",
      "type": "hold",
      "duration": 1074
    },
    {
      "time": 44883,
      "lane": "f",
      "type": "hold",
      "duration": 987
    },
    {
      "time": 44901,
      "lane": "k",
      "type": "hold",
      "duration": 1052
    },
    {
      "time": 46413,
      "lane": "k",
      "type": "hold",
      "duration": 489
    },
    {
      "time": 46424,
      "lane": "d",
      "type": "hold",
      "duration": 516
    },
    {
      "time": 47197,
      "lane": "f",
      "type": "hold",
      "duration": 376
    },
    {
      "time": 47216,
      "lane": "j",
      "type": "hold",
      "duration": 316
    },
    {
      "time": 47874,
      "lane": "k"
    },
    {
      "time": 47891,
      "lane": "d"
    },
    {
      "time": 48232,
      "lane": "f"
    },
    {
      "time": 48249,
      "lane": "j"
    },
    {
      "time": 48588,
      "lane": "f"
    },
    {
      "time": 48642,
      "lane": "k"
    },
    {
      "time": 49046,
      "lane": "j"
    },
    {
      "time": 49056,
      "lane": "d"
    },
    {
      "time": 49404,
      "lane": "k",
      "type": "hold",
      "duration": 430
    },
    {
      "time": 49418,
      "lane": "d",
      "type": "hold",
      "duration": 389
    },
    {
      "time": 49784,
      "lane": "f",
      "type": "hold",
      "duration": 723
    },
    {
      "time": 50166,
      "lane": "j",
      "type": "hold",
      "duration": 389
    },
    {
      "time": 50557,
      "lane": "k"
    },
    {
      "time": 50729,
      "lane": "f"
    },
    {
      "time": 50840,
      "lane": "j"
    },
    {
      "time": 50929,
      "lane": "f"
    },
    {
      "time": 51146,
      "lane": "j"
    },
    {
      "time": 51328,
      "lane": "d",
      "type": "hold",
      "duration": 399
    },
    {
      "time": 51655,
      "lane": "k",
      "type": "hold",
      "duration": 378
    },
    {
      "time": 52009,
      "lane": "f",
      "type": "hold",
      "duration": 382
    },
    {
      "time": 52420,
      "lane": "j"
    },
    {
      "time": 52590,
      "lane": "d"
    },
    {
      "time": 52771,
      "lane": "k"
    },
    {
      "time": 52935,
      "lane": "d"
    },
    {
      "time": 53158,
      "lane": "j",
      "type": "hold",
      "duration": 384
    },
    {
      "time": 53523,
      "lane": "f",
      "type": "hold",
      "duration": 354
    },
    {
      "time": 53927,
      "lane": "k",
      "type": "hold",
      "duration": 495
    },
    {
      "time": 54483,
      "lane": "f"
    },
    {
      "time": 54543,
      "lane": "j"
    },
    {
      "time": 54638,
      "lane": "f",
      "type": "hold",
      "duration": 337
    },
    {
      "time": 54962,
      "lane": "d",
      "type": "hold",
      "duration": 444
    },
    {
      "time": 55393,
      "lane": "k",
      "type": "hold",
      "duration": 382
    },
    {
      "time": 55778,
      "lane": "d",
      "type": "hold",
      "duration": 353
    },
    {
      "time": 56155,
      "lane": "k",
      "type": "hold",
      "duration": 359
    },
    {
      "time": 56487,
      "lane": "f"
    },
    {
      "time": 56540,
      "lane": "j"
    },
    {
      "time": 56698,
      "lane": "k"
    },
    {
      "time": 56721,
      "lane": "f"
    },
    {
      "time": 56808,
      "lane": "j"
    },
    {
      "time": 56930,
      "lane": "f",
      "type": "hold",
      "duration": 357
    },
    {
      "time": 57276,
      "lane": "j",
      "type": "hold",
      "duration": 341
    },
    {
      "time": 57633,
      "lane": "d",
      "type": "hold",
      "duration": 366
    },
    {
      "time": 58025,
      "lane": "k"
    },
    {
      "time": 58422,
      "lane": "d"
    },
    {
      "time": 58475,
      "lane": "k"
    },
    {
      "time": 58604,
      "lane": "k"
    },
    {
      "time": 58800,
      "lane": "d"
    },
    {
      "time": 59012,
      "lane": "j"
    },
    {
      "time": 59146,
      "lane": "f",
      "type": "hold",
      "duration": 380
    },
    {
      "time": 59909,
      "lane": "k"
    },
    {
      "time": 60071,
      "lane": "d"
    },
    {
      "time": 60254,
      "lane": "j"
    },
    {
      "time": 60392,
      "lane": "d"
    },
    {
      "time": 60523,
      "lane": "j"
    },
    {
      "time": 60612,
      "lane": "d"
    },
    {
      "time": 60671,
      "lane": "k",
      "type": "hold",
      "duration": 674
    },
    {
      "time": 61394,
      "lane": "f",
      "type": "hold",
      "duration": 1097
    },
    {
      "time": 62786,
      "lane": "f"
    },
    {
      "time": 62924,
      "lane": "j",
      "type": "hold",
      "duration": 451
    },
    {
      "time": 63528,
      "lane": "f"
    },
    {
      "time": 63663,
      "lane": "j",
      "type": "hold",
      "duration": 455
    },
    {
      "time": 64301,
      "lane": "f"
    },
    {
      "time": 64436,
      "lane": "j",
      "type": "hold",
      "duration": 1487
    },
    {
      "time": 65874,
      "lane": "f"
    },
    {
      "time": 65899,
      "lane": "k"
    },
    {
      "time": 66614,
      "lane": "d",
      "type": "hold",
      "duration": 731
    },
    {
      "time": 66639,
      "lane": "k",
      "type": "hold",
      "duration": 708
    },
    {
      "time": 67314,
      "lane": "j"
    },
    {
      "time": 68079,
      "lane": "f",
      "type": "hold",
      "duration": 799
    },
    {
      "time": 68819,
      "lane": "k"
    },
    {
      "time": 69583,
      "lane": "d",
      "type": "hold",
      "duration": 817
    },
    {
      "time": 69607,
      "lane": "j",
      "type": "hold",
      "duration": 809
    },
    {
      "time": 70330,
      "lane": "f",
      "type": "hold",
      "duration": 871
    },
    {
      "time": 70385,
      "lane": "k",
      "type": "hold",
      "duration": 793
    },
    {
      "time": 71835,
      "lane": "f"
    },
    {
      "time": 71854,
      "lane": "k",
      "type": "hold",
      "duration": 778
    },
    {
      "time": 72582,
      "lane": "f"
    },
    {
      "time": 72605,
      "lane": "j",
      "type": "hold",
      "duration": 752
    },
    {
      "time": 73347,
      "lane": "d",
      "type": "hold",
      "duration": 538
    },
    {
      "time": 74130,
      "lane": "d"
    },
    {
      "time": 74160,
      "lane": "k"
    },
    {
      "time": 74494,
      "lane": "f"
    },
    {
      "time": 74521,
      "lane": "j"
    },
    {
      "time": 74874,
      "lane": "k",
      "type": "hold",
      "duration": 429
    },
    {
      "time": 74906,
      "lane": "f",
      "type": "hold",
      "duration": 415
    },
    {
      "time": 75659,
      "lane": "j"
    },
    {
      "time": 75671,
      "lane": "d",
      "type": "hold",
      "duration": 728
    },
    {
      "time": 76003,
      "lane": "k",
      "type": "hold",
      "duration": 738
    },
    {
      "time": 76383,
      "lane": "f",
      "type": "hold",
      "duration": 738
    },
    {
      "time": 76778,
      "lane": "j",
      "type": "hold",
      "duration": 360
    },
    {
      "time": 77158,
      "lane": "k"
    },
    {
      "time": 77662,
      "lane": "j"
    },
    {
      "time": 77922,
      "lane": "k",
      "type": "hold",
      "duration": 330
    },
    {
      "time": 78267,
      "lane": "j",
      "type": "hold",
      "duration": 366
    },
    {
      "time": 78291,
      "lane": "f",
      "type": "hold",
      "duration": 360
    },
    {
      "time": 78991,
      "lane": "k",
      "type": "hold",
      "duration": 371
    },
    {
      "time": 79300,
      "lane": "d",
      "type": "hold",
      "duration": 407
    },
    {
      "time": 79718,
      "lane": "j"
    },
    {
      "time": 80117,
      "lane": "f",
      "type": "hold",
      "duration": 376
    },
    {
      "time": 80138,
      "lane": "k",
      "type": "hold",
      "duration": 389
    },
    {
      "time": 80552,
      "lane": "j",
      "type": "hold",
      "duration": 321
    },
    {
      "time": 80909,
      "lane": "d",
      "type": "hold",
      "duration": 374
    },
    {
      "time": 81256,
      "lane": "k",
      "type": "hold",
      "duration": 392
    },
    {
      "time": 81605,
      "lane": "f",
      "type": "hold",
      "duration": 405
    },
    {
      "time": 81983,
      "lane": "j"
    },
    {
      "time": 82361,
      "lane": "k",
      "type": "hold",
      "duration": 764
    },
    {
      "time": 82389,
      "lane": "f",
      "type": "hold",
      "duration": 774
    },
    {
      "time": 83534,
      "lane": "d"
    },
    {
      "time": 83555,
      "lane": "k"
    },
    {
      "time": 83877,
      "lane": "f"
    },
    {
      "time": 83886,
      "lane": "j"
    },
    {
      "time": 84259,
      "lane": "k"
    },
    {
      "time": 84279,
      "lane": "d"
    },
    {
      "time": 84641,
      "lane": "f",
      "type": "hold",
      "duration": 358
    },
    {
      "time": 84666,
      "lane": "k",
      "type": "hold",
      "duration": 306
    },
    {
      "time": 84996,
      "lane": "d"
    },
    {
      "time": 85014,
      "lane": "j"
    },
    {
      "time": 85389,
      "lane": "f",
      "type": "hold",
      "duration": 888
    },
    {
      "time": 85413,
      "lane": "k",
      "type": "hold",
      "duration": 838
    },
    {
      "time": 86596,
      "lane": "f"
    },
    {
      "time": 86866,
      "lane": "k",
      "type": "hold",
      "duration": 356
    },
    {
      "time": 87263,
      "lane": "d",
      "type": "hold",
      "duration": 415
    },
    {
      "time": 87584,
      "lane": "j",
      "type": "hold",
      "duration": 438
    },
    {
      "time": 87990,
      "lane": "f",
      "type": "hold",
      "duration": 377
    },
    {
      "time": 88372,
      "lane": "k",
      "type": "hold",
      "duration": 1536
    },
    {
      "time": 89157,
      "lane": "j",
      "type": "hold",
      "duration": 778
    },
    {
      "time": 89951,
      "lane": "f",
      "type": "hold",
      "duration": 339
    },
    {
      "time": 90195,
      "lane": "d",
      "type": "hold",
      "duration": 613
    },
    {
      "time": 90755,
      "lane": "j",
      "type": "hold",
      "duration": 406
    },
    {
      "time": 91430,
      "lane": "f",
      "type": "hold",
      "duration": 522
    },
    {
      "time": 92025,
      "lane": "j"
    },
    {
      "time": 92088,
      "lane": "d",
      "type": "hold",
      "duration": 843
    },
    {
      "time": 92872,
      "lane": "f",
      "type": "hold",
      "duration": 456
    },
    {
      "time": 93232,
      "lane": "d",
      "type": "hold",
      "duration": 785
    },
    {
      "time": 94340,
      "lane": "j",
      "type": "hold",
      "duration": 2712
    },
    {
      "time": 95887,
      "lane": "f",
      "type": "hold",
      "duration": 322
    },
    {
      "time": 96180,
      "lane": "d",
      "type": "hold",
      "duration": 470
    },
    {
      "time": 97080,
      "lane": "f"
    },
    {
      "time": 97227,
      "lane": "d"
    },
    {
      "time": 97384,
      "lane": "f",
      "type": "hold",
      "duration": 1004
    },
    {
      "time": 98904,
      "lane": "d"
    },
    {
      "time": 99243,
      "lane": "d"
    },
    {
      "time": 99626,
      "lane": "f"
    },
    {
      "time": 100007,
      "lane": "f"
    },
    {
      "time": 100341,
      "lane": "f"
    },
    {
      "time": 100439,
      "lane": "j"
    },
    {
      "time": 100600,
      "lane": "k"
    },
    {
      "time": 100860,
      "lane": "k"
    },
    {
      "time": 100931,
      "lane": "d"
    },
    {
      "time": 101042,
      "lane": "k"
    },
    {
      "time": 101163,
      "lane": "k"
    },
    {
      "time": 101357,
      "lane": "k"
    },
    {
      "time": 101372,
      "lane": "d"
    },
    {
      "time": 101482,
      "lane": "j"
    },
    {
      "time": 101524,
      "lane": "f"
    },
    {
      "time": 101853,
      "lane": "f"
    },
    {
      "time": 101866,
      "lane": "j"
    },
    {
      "time": 101979,
      "lane": "j"
    },
    {
      "time": 102012,
      "lane": "f"
    },
    {
      "time": 102134,
      "lane": "k"
    },
    {
      "time": 102265,
      "lane": "d"
    },
    {
      "time": 102338,
      "lane": "j"
    },
    {
      "time": 102528,
      "lane": "d"
    },
    {
      "time": 102643,
      "lane": "j"
    },
    {
      "time": 102741,
      "lane": "j"
    },
    {
      "time": 102826,
      "lane": "j"
    },
    {
      "time": 102924,
      "lane": "k"
    },
    {
      "time": 102997,
      "lane": "d"
    },
    {
      "time": 103199,
      "lane": "f"
    },
    {
      "time": 103443,
      "lane": "f"
    },
    {
      "time": 103476,
      "lane": "j"
    },
    {
      "time": 103760,
      "lane": "j"
    },
    {
      "time": 103895,
      "lane": "k"
    },
    {
      "time": 103932,
      "lane": "d"
    },
    {
      "time": 104326,
      "lane": "j"
    },
    {
      "time": 104439,
      "lane": "j"
    },
    {
      "time": 104522,
      "lane": "d"
    },
    {
      "time": 104773,
      "lane": "j"
    },
    {
      "time": 104818,
      "lane": "d"
    },
    {
      "time": 104880,
      "lane": "k"
    },
    {
      "time": 104979,
      "lane": "f"
    },
    {
      "time": 104984,
      "lane": "j"
    },
    {
      "time": 105148,
      "lane": "j"
    },
    {
      "time": 105226,
      "lane": "j"
    },
    {
      "time": 105272,
      "lane": "k"
    },
    {
      "time": 105308,
      "lane": "d"
    },
    {
      "time": 105400,
      "lane": "j"
    },
    {
      "time": 105509,
      "lane": "d"
    },
    {
      "time": 105558,
      "lane": "k"
    },
    {
      "time": 105829,
      "lane": "f"
    },
    {
      "time": 105939,
      "lane": "j"
    },
    {
      "time": 106067,
      "lane": "j"
    },
    {
      "time": 106198,
      "lane": "j"
    },
    {
      "time": 106356,
      "lane": "d",
      "type": "hold",
      "duration": 1278
    },
    {
      "time": 107020,
      "lane": "f",
      "type": "hold",
      "duration": 755
    },
    {
      "time": 107794,
      "lane": "k"
    },
    {
      "time": 107898,
      "lane": "j",
      "type": "hold",
      "duration": 359
    },
    {
      "time": 108242,
      "lane": "f",
      "type": "hold",
      "duration": 393
    },
    {
      "time": 108600,
      "lane": "k",
      "type": "hold",
      "duration": 1461
    },
    {
      "time": 108966,
      "lane": "f",
      "type": "hold",
      "duration": 421
    },
    {
      "time": 109359,
      "lane": "d",
      "type": "hold",
      "duration": 778
    },
    {
      "time": 109411,
      "lane": "j",
      "type": "hold",
      "duration": 701
    },
    {
      "time": 110128,
      "lane": "f",
      "type": "hold",
      "duration": 744
    },
    {
      "time": 110330,
      "lane": "j",
      "type": "hold",
      "duration": 576
    },
    {
      "time": 110926,
      "lane": "d",
      "type": "hold",
      "duration": 819
    },
    {
      "time": 112313,
      "lane": "f",
      "type": "hold",
      "duration": 944
    },
    {
      "time": 112387,
      "lane": "k"
    },
    {
      "time": 112474,
      "lane": "j",
      "type": "hold",
      "duration": 832
    },
    {
      "time": 113839,
      "lane": "d",
      "type": "hold",
      "duration": 317
    },
    {
      "time": 113886,
      "lane": "k"
    },
    {
      "time": 114476,
      "lane": "f",
      "type": "hold",
      "duration": 543
    },
    {
      "time": 114540,
      "lane": "j",
      "type": "hold",
      "duration": 406
    },
    {
      "time": 115276,
      "lane": "f",
      "type": "hold",
      "duration": 522
    },
    {
      "time": 115342,
      "lane": "k",
      "type": "hold",
      "duration": 488
    },
    {
      "time": 116112,
      "lane": "d",
      "type": "hold",
      "duration": 544
    },
    {
      "time": 116144,
      "lane": "j",
      "type": "hold",
      "duration": 647
    },
    {
      "time": 116870,
      "lane": "f"
    },
    {
      "time": 116941,
      "lane": "k"
    },
    {
      "time": 117085,
      "lane": "k"
    },
    {
      "time": 117210,
      "lane": "f"
    },
    {
      "time": 117232,
      "lane": "k"
    },
    {
      "time": 117394,
      "lane": "j"
    },
    {
      "time": 117498,
      "lane": "d"
    },
    {
      "time": 117605,
      "lane": "j"
    },
    {
      "time": 117749,
      "lane": "j"
    },
    {
      "time": 117891,
      "lane": "k"
    },
    {
      "time": 117935,
      "lane": "d",
      "type": "hold",
      "duration": 430
    },
    {
      "time": 118403,
      "lane": "f"
    },
    {
      "time": 118418,
      "lane": "j"
    },
    {
      "time": 118551,
      "lane": "j"
    },
    {
      "time": 118626,
      "lane": "f"
    },
    {
      "time": 118678,
      "lane": "j"
    },
    {
      "time": 118835,
      "lane": "j"
    },
    {
      "time": 118861,
      "lane": "f"
    },
    {
      "time": 119005,
      "lane": "d"
    },
    {
      "time": 119212,
      "lane": "f"
    },
    {
      "time": 119352,
      "lane": "d"
    },
    {
      "time": 119486,
      "lane": "f"
    },
    {
      "time": 119561,
      "lane": "j"
    },
    {
      "time": 119672,
      "lane": "f"
    },
    {
      "time": 119877,
      "lane": "j"
    },
    {
      "time": 119966,
      "lane": "f"
    },
    {
      "time": 120091,
      "lane": "d"
    },
    {
      "time": 120266,
      "lane": "k"
    },
    {
      "time": 120435,
      "lane": "k"
    },
    {
      "time": 120657,
      "lane": "f"
    },
    {
      "time": 120789,
      "lane": "j"
    },
    {
      "time": 120962,
      "lane": "j"
    },
    {
      "time": 121010,
      "lane": "f"
    },
    {
      "time": 121410,
      "lane": "k",
      "type": "hold",
      "duration": 2693
    },
    {
      "time": 122795,
      "lane": "d",
      "type": "hold",
      "duration": 949
    },
    {
      "time": 122829,
      "lane": "j",
      "type": "hold",
      "duration": 1299
    },
    {
      "time": 123250,
      "lane": "f"
    },
    {
      "time": 123660,
      "lane": "f"
    },
    {
      "time": 123783,
      "lane": "d"
    },
    {
      "time": 124014,
      "lane": "f"
    },
    {
      "time": 124396,
      "lane": "f"
    },
    {
      "time": 124431,
      "lane": "k"
    },
    {
      "time": 124580,
      "lane": "k"
    },
    {
      "time": 124605,
      "lane": "f"
    },
    {
      "time": 124814,
      "lane": "j"
    },
    {
      "time": 124840,
      "lane": "d"
    },
    {
      "time": 124973,
      "lane": "j"
    },
    {
      "time": 125022,
      "lane": "d"
    },
    {
      "time": 125194,
      "lane": "f",
      "type": "hold",
      "duration": 426
    },
    {
      "time": 125235,
      "lane": "k"
    },
    {
      "time": 125393,
      "lane": "k"
    },
    {
      "time": 125590,
      "lane": "j"
    },
    {
      "time": 125637,
      "lane": "d",
      "type": "hold",
      "duration": 493
    },
    {
      "time": 125747,
      "lane": "j"
    },
    {
      "time": 125899,
      "lane": "j"
    },
    {
      "time": 126057,
      "lane": "j"
    },
    {
      "time": 126225,
      "lane": "f"
    },
    {
      "time": 126462,
      "lane": "j"
    },
    {
      "time": 126642,
      "lane": "f"
    },
    {
      "time": 126822,
      "lane": "j"
    },
    {
      "time": 127056,
      "lane": "d"
    },
    {
      "time": 127227,
      "lane": "k"
    },
    {
      "time": 127396,
      "lane": "d"
    },
    {
      "time": 127572,
      "lane": "k"
    },
    {
      "time": 127706,
      "lane": "k"
    },
    {
      "time": 127841,
      "lane": "f"
    },
    {
      "time": 127925,
      "lane": "j"
    },
    {
      "time": 127961,
      "lane": "k"
    },
    {
      "time": 128062,
      "lane": "j"
    },
    {
      "time": 128224,
      "lane": "f"
    },
    {
      "time": 128247,
      "lane": "d"
    },
    {
      "time": 128554,
      "lane": "k"
    },
    {
      "time": 128585,
      "lane": "j"
    },
    {
      "time": 128727,
      "lane": "k"
    },
    {
      "time": 128740,
      "lane": "j"
    },
    {
      "time": 128915,
      "lane": "f"
    },
    {
      "time": 129072,
      "lane": "j"
    },
    {
      "time": 129229,
      "lane": "j"
    },
    {
      "time": 129341,
      "lane": "f"
    },
    {
      "time": 129529,
      "lane": "k"
    },
    {
      "time": 129683,
      "lane": "f"
    },
    {
      "time": 129851,
      "lane": "k"
    },
    {
      "time": 129991,
      "lane": "d"
    },
    {
      "time": 130179,
      "lane": "k"
    },
    {
      "time": 130427,
      "lane": "f"
    },
    {
      "time": 130472,
      "lane": "k"
    },
    {
      "time": 131150,
      "lane": "d"
    },
    {
      "time": 131178,
      "lane": "k"
    },
    {
      "time": 131182,
      "lane": "j"
    },
    {
      "time": 131864,
      "lane": "f"
    },
    {
      "time": 131906,
      "lane": "k"
    },
    {
      "time": 132042,
      "lane": "d"
    },
    {
      "time": 132654,
      "lane": "d"
    },
    {
      "time": 132716,
      "lane": "j"
    },
    {
      "time": 133376,
      "lane": "f"
    },
    {
      "time": 133397,
      "lane": "k"
    },
    {
      "time": 133734,
      "lane": "d"
    },
    {
      "time": 133770,
      "lane": "j"
    },
    {
      "time": 134140,
      "lane": "f"
    },
    {
      "time": 134164,
      "lane": "k"
    },
    {
      "time": 134476,
      "lane": "d",
      "type": "hold",
      "duration": 441
    },
    {
      "time": 134533,
      "lane": "k"
    },
    {
      "time": 134881,
      "lane": "f"
    },
    {
      "time": 134921,
      "lane": "j"
    },
    {
      "time": 135222,
      "lane": "k"
    },
    {
      "time": 135268,
      "lane": "d",
      "type": "hold",
      "duration": 339
    },
    {
      "time": 135624,
      "lane": "j",
      "type": "hold",
      "duration": 340
    },
    {
      "time": 135652,
      "lane": "k",
      "type": "hold",
      "duration": 340
    },
    {
      "time": 135996,
      "lane": "d"
    },
    {
      "time": 136025,
      "lane": "f"
    },
    {
      "time": 136392,
      "lane": "j"
    },
    {
      "time": 136455,
      "lane": "f"
    },
    {
      "time": 136539,
      "lane": "j"
    },
    {
      "time": 136643,
      "lane": "j"
    },
    {
      "time": 136788,
      "lane": "k"
    },
    {
      "time": 136829,
      "lane": "f"
    },
    {
      "time": 136988,
      "lane": "d"
    },
    {
      "time": 137183,
      "lane": "k"
    },
    {
      "time": 137389,
      "lane": "d"
    },
    {
      "time": 137538,
      "lane": "k"
    },
    {
      "time": 137698,
      "lane": "k"
    },
    {
      "time": 137868,
      "lane": "k"
    },
    {
      "time": 137966,
      "lane": "k"
    },
    {
      "time": 138101,
      "lane": "k"
    },
    {
      "time": 138287,
      "lane": "j"
    },
    {
      "time": 138438,
      "lane": "k"
    },
    {
      "time": 138571,
      "lane": "j"
    },
    {
      "time": 138600,
      "lane": "f",
      "type": "hold",
      "duration": 422
    },
    {
      "time": 138625,
      "lane": "d"
    },
    {
      "time": 138975,
      "lane": "k"
    },
    {
      "time": 139109,
      "lane": "k"
    },
    {
      "time": 139274,
      "lane": "k"
    },
    {
      "time": 139290,
      "lane": "j"
    },
    {
      "time": 139373,
      "lane": "d",
      "type": "hold",
      "duration": 343
    },
    {
      "time": 139553,
      "lane": "j"
    },
    {
      "time": 139721,
      "lane": "j"
    },
    {
      "time": 139825,
      "lane": "j"
    },
    {
      "time": 140146,
      "lane": "d",
      "type": "hold",
      "duration": 307
    },
    {
      "time": 140340,
      "lane": "k"
    },
    {
      "time": 140561,
      "lane": "d"
    },
    {
      "time": 140770,
      "lane": "k"
    },
    {
      "time": 140982,
      "lane": "f"
    },
    {
      "time": 141115,
      "lane": "j"
    },
    {
      "time": 141244,
      "lane": "j"
    },
    {
      "time": 141375,
      "lane": "j"
    },
    {
      "time": 141527,
      "lane": "j"
    },
    {
      "time": 141546,
      "lane": "k",
      "type": "hold",
      "duration": 361
    },
    {
      "time": 141572,
      "lane": "d",
      "type": "hold",
      "duration": 494
    },
    {
      "time": 142034,
      "lane": "j",
      "type": "hold",
      "duration": 316
    },
    {
      "time": 142383,
      "lane": "f"
    },
    {
      "time": 142809,
      "lane": "k"
    },
    {
      "time": 142942,
      "lane": "k"
    },
    {
      "time": 143062,
      "lane": "f"
    },
    {
      "time": 143234,
      "lane": "k"
    },
    {
      "time": 143458,
      "lane": "f"
    },
    {
      "time": 143633,
      "lane": "k"
    },
    {
      "time": 143839,
      "lane": "d"
    },
    {
      "time": 143872,
      "lane": "j"
    },
    {
      "time": 144011,
      "lane": "j"
    },
    {
      "time": 144143,
      "lane": "j"
    },
    {
      "time": 144255,
      "lane": "d"
    },
    {
      "time": 144438,
      "lane": "d"
    },
    {
      "time": 144591,
      "lane": "d"
    },
    {
      "time": 144782,
      "lane": "f"
    },
    {
      "time": 145008,
      "lane": "k"
    },
    {
      "time": 145090,
      "lane": "d"
    },
    {
      "time": 145241,
      "lane": "k"
    },
    {
      "time": 145326,
      "lane": "d"
    },
    {
      "time": 145608,
      "lane": "j"
    },
    {
      "time": 145780,
      "lane": "d"
    },
    {
      "time": 146038,
      "lane": "f"
    },
    {
      "time": 146199,
      "lane": "k"
    },
    {
      "time": 146239,
      "lane": "f"
    },
    {
      "time": 146854,
      "lane": "d",
      "type": "hold",
      "duration": 552
    },
    {
      "time": 147371,
      "lane": "f"
    },
    {
      "time": 147436,
      "lane": "j"
    },
    {
      "time": 147505,
      "lane": "f"
    },
    {
      "time": 147566,
      "lane": "j",
      "type": "hold",
      "duration": 787
    },
    {
      "time": 148410,
      "lane": "d",
      "type": "hold",
      "duration": 1422
    },
    {
      "time": 149106,
      "lane": "f"
    },
    {
      "time": 149251,
      "lane": "j"
    },
    {
      "time": 149546,
      "lane": "f"
    },
    {
      "time": 149582,
      "lane": "k"
    },
    {
      "time": 149722,
      "lane": "k"
    },
    {
      "time": 149952,
      "lane": "j"
    },
    {
      "time": 150109,
      "lane": "f"
    },
    {
      "time": 150152,
      "lane": "j"
    },
    {
      "time": 150311,
      "lane": "j"
    },
    {
      "time": 150694,
      "lane": "d",
      "type": "hold",
      "duration": 387
    },
    {
      "time": 150729,
      "lane": "k"
    },
    {
      "time": 150867,
      "lane": "k"
    },
    {
      "time": 151039,
      "lane": "k"
    },
    {
      "time": 151391,
      "lane": "f",
      "type": "hold",
      "duration": 752
    },
    {
      "time": 151436,
      "lane": "j"
    },
    {
      "time": 151578,
      "lane": "j"
    },
    {
      "time": 151673,
      "lane": "k"
    },
    {
      "time": 151935,
      "lane": "k"
    },
    {
      "time": 152165,
      "lane": "k"
    },
    {
      "time": 152193,
      "lane": "f",
      "type": "hold",
      "duration": 359
    },
    {
      "time": 152276,
      "lane": "j"
    },
    {
      "time": 152499,
      "lane": "k"
    },
    {
      "time": 152669,
      "lane": "f"
    },
    {
      "time": 152687,
      "lane": "j"
    },
    {
      "time": 152755,
      "lane": "d"
    },
    {
      "time": 152879,
      "lane": "k"
    },
    {
      "time": 153005,
      "lane": "d"
    },
    {
      "time": 153620,
      "lane": "f",
      "type": "hold",
      "duration": 771
    },
    {
      "time": 153658,
      "lane": "k",
      "type": "hold",
      "duration": 700
    },
    {
      "time": 154347,
      "lane": "j",
      "type": "hold",
      "duration": 549
    },
    {
      "time": 154863,
      "lane": "k"
    },
    {
      "time": 155009,
      "lane": "j"
    },
    {
      "time": 155051,
      "lane": "f",
      "type": "hold",
      "duration": 477
    },
    {
      "time": 155439,
      "lane": "k"
    },
    {
      "time": 155849,
      "lane": "d",
      "type": "hold",
      "duration": 1168
    },
    {
      "time": 155885,
      "lane": "k"
    },
    {
      "time": 156095,
      "lane": "k"
    },
    {
      "time": 156176,
      "lane": "k"
    },
    {
      "time": 156340,
      "lane": "j"
    },
    {
      "time": 156479,
      "lane": "k"
    },
    {
      "time": 156634,
      "lane": "j"
    },
    {
      "time": 156669,
      "lane": "f",
      "type": "hold",
      "duration": 666
    },
    {
      "time": 157061,
      "lane": "k"
    },
    {
      "time": 157374,
      "lane": "k",
      "type": "hold",
      "duration": 1379
    },
    {
      "time": 158051,
      "lane": "j"
    },
    {
      "time": 158222,
      "lane": "f"
    },
    {
      "time": 158468,
      "lane": "j"
    },
    {
      "time": 158794,
      "lane": "d"
    },
    {
      "time": 158911,
      "lane": "k"
    },
    {
      "time": 159071,
      "lane": "k"
    },
    {
      "time": 159206,
      "lane": "k"
    },
    {
      "time": 159350,
      "lane": "k"
    },
    {
      "time": 159514,
      "lane": "d",
      "type": "hold",
      "duration": 594
    },
    {
      "time": 159576,
      "lane": "j",
      "type": "hold",
      "duration": 479
    },
    {
      "time": 160372,
      "lane": "f",
      "type": "hold",
      "duration": 447
    },
    {
      "time": 160755,
      "lane": "k",
      "type": "hold",
      "duration": 676
    },
    {
      "time": 161076,
      "lane": "j",
      "type": "hold",
      "duration": 398
    },
    {
      "time": 161506,
      "lane": "d"
    },
    {
      "time": 161577,
      "lane": "f",
      "type": "hold",
      "duration": 335
    },
    {
      "time": 161904,
      "lane": "j",
      "type": "hold",
      "duration": 434
    },
    {
      "time": 162292,
      "lane": "d",
      "type": "hold",
      "duration": 313
    },
    {
      "time": 162646,
      "lane": "k",
      "type": "hold",
      "duration": 398
    },
    {
      "time": 163032,
      "lane": "f"
    },
    {
      "time": 163300,
      "lane": "j"
    },
    {
      "time": 163362,
      "lane": "d"
    },
    {
      "time": 163434,
      "lane": "j",
      "type": "hold",
      "duration": 361
    },
    {
      "time": 163804,
      "lane": "k",
      "type": "hold",
      "duration": 340
    },
    {
      "time": 164101,
      "lane": "f",
      "type": "hold",
      "duration": 423
    },
    {
      "time": 164495,
      "lane": "j",
      "type": "hold",
      "duration": 381
    },
    {
      "time": 164906,
      "lane": "d",
      "type": "hold",
      "duration": 323
    },
    {
      "time": 165185,
      "lane": "k",
      "type": "hold",
      "duration": 765
    },
    {
      "time": 165546,
      "lane": "d",
      "type": "hold",
      "duration": 507
    },
    {
      "time": 166008,
      "lane": "f"
    },
    {
      "time": 166049,
      "lane": "j"
    },
    {
      "time": 166206,
      "lane": "j"
    },
    {
      "time": 166305,
      "lane": "f",
      "type": "hold",
      "duration": 455
    },
    {
      "time": 166333,
      "lane": "k"
    },
    {
      "time": 166809,
      "lane": "k"
    },
    {
      "time": 167109,
      "lane": "d",
      "type": "hold",
      "duration": 399
    },
    {
      "time": 167539,
      "lane": "j"
    },
    {
      "time": 168067,
      "lane": "f"
    },
    {
      "time": 168213,
      "lane": "k"
    },
    {
      "time": 168258,
      "lane": "d"
    },
    {
      "time": 168297,
      "lane": "j"
    },
    {
      "time": 168621,
      "lane": "d",
      "type": "hold",
      "duration": 343
    },
    {
      "time": 169004,
      "lane": "k",
      "type": "hold",
      "duration": 388
    },
    {
      "time": 169333,
      "lane": "f",
      "type": "hold",
      "duration": 871
    },
    {
      "time": 170480,
      "lane": "d"
    },
    {
      "time": 170488,
      "lane": "k"
    },
    {
      "time": 170857,
      "lane": "f"
    },
    {
      "time": 170898,
      "lane": "j"
    },
    {
      "time": 171219,
      "lane": "k",
      "type": "hold",
      "duration": 437
    },
    {
      "time": 171595,
      "lane": "f",
      "type": "hold",
      "duration": 409
    },
    {
      "time": 171965,
      "lane": "j"
    },
    {
      "time": 172369,
      "lane": "d",
      "type": "hold",
      "duration": 763
    },
    {
      "time": 172401,
      "lane": "k",
      "type": "hold",
      "duration": 767
    },
    {
      "time": 173468,
      "lane": "j"
    },
    {
      "time": 173512,
      "lane": "f"
    },
    {
      "time": 173871,
      "lane": "j"
    },
    {
      "time": 173913,
      "lane": "k"
    },
    {
      "time": 174229,
      "lane": "d"
    },
    {
      "time": 174274,
      "lane": "f"
    },
    {
      "time": 174609,
      "lane": "k"
    },
    {
      "time": 174658,
      "lane": "d"
    },
    {
      "time": 174964,
      "lane": "f",
      "type": "hold",
      "duration": 345
    },
    {
      "time": 174998,
      "lane": "j",
      "type": "hold",
      "duration": 359
    },
    {
      "time": 175384,
      "lane": "k",
      "type": "hold",
      "duration": 2965
    },
    {
      "time": 176147,
      "lane": "f",
      "type": "hold",
      "duration": 875
    },
    {
      "time": 176887,
      "lane": "d",
      "type": "hold",
      "duration": 1687
    },
    {
      "time": 177060,
      "lane": "f"
    },
    {
      "time": 177676,
      "lane": "j",
      "type": "hold",
      "duration": 1499
    },
    {
      "time": 179162,
      "lane": "f",
      "type": "hold",
      "duration": 767
    },
    {
      "time": 179986,
      "lane": "k",
      "type": "hold",
      "duration": 728
    },
    {
      "time": 180669,
      "lane": "d",
      "type": "hold",
      "duration": 782
    },
    {
      "time": 181462,
      "lane": "f",
      "type": "hold",
      "duration": 2267
    },
    {
      "time": 181499,
      "lane": "j",
      "type": "hold",
      "duration": 2178
    },
    {
      "time": 184063,
      "lane": "k"
    },
    {
      "time": 184181,
      "lane": "j"
    },
    {
      "time": 184377,
      "lane": "f"
    },
    {
      "time": 184445,
      "lane": "d",
      "type": "hold",
      "duration": 1267
    },
    {
      "time": 185904,
      "lane": "f",
      "type": "hold",
      "duration": 412
    },
    {
      "time": 185920,
      "lane": "j",
      "type": "hold",
      "duration": 439
    },
    {
      "time": 186587,
      "lane": "d",
      "type": "hold",
      "duration": 473
    },
    {
      "time": 186634,
      "lane": "f",
      "type": "hold",
      "duration": 463
    },
    {
      "time": 187442,
      "lane": "k",
      "type": "hold",
      "duration": 911
    },
    {
      "time": 187475,
      "lane": "j",
      "type": "hold",
      "duration": 866
    },
    {
      "time": 188860,
      "lane": "d",
      "type": "hold",
      "duration": 760
    },
    {
      "time": 188869,
      "lane": "k",
      "type": "hold",
      "duration": 801
    },
    {
      "time": 190325,
      "lane": "f",
      "type": "hold",
      "duration": 329
    },
    {
      "time": 190359,
      "lane": "k",
      "type": "hold",
      "duration": 565
    },
    {
      "time": 190364,
      "lane": "j",
      "type": "hold",
      "duration": 574
    },
    {
      "time": 190699,
      "lane": "f"
    },
    {
      "time": 191150,
      "lane": "d",
      "type": "hold",
      "duration": 972
    },
    {
      "time": 191190,
      "lane": "f",
      "type": "hold",
      "duration": 938
    },
    {
      "time": 191355,
      "lane": "j",
      "type": "hold",
      "duration": 716
    },
    {
      "time": 192610,
      "lane": "f"
    },
    {
      "time": 192660,
      "lane": "k"
    },
    {
      "time": 192665,
      "lane": "j"
    },
    {
      "time": 193364,
      "lane": "d",
      "type": "hold",
      "duration": 3368
    },
    {
      "time": 193366,
      "lane": "k",
      "type": "hold",
      "duration": 3320
    }
  ]
}